<Properties StartupConfiguration="{BC7B256C-DA7A-4802-BE85-D9005AB254B1}|http">
  <MonoDevelop.Ide.DebuggingService.PinnedWatches />
  <MonoDevelop.Ide.Workspace ActiveConfiguration="Debug" />
  <MonoDevelop.Ide.ItemProperties.serverV2 PreferredExecutionTarget="/System/Volumes/Preboot/Cryptexes/App/System/Applications/Safari.app" />
  <MultiItemStartupConfigurations />
  <MonoDevelop.Ide.DebuggingService.Breakpoints>
    <BreakpointStore />
  </MonoDevelop.Ide.DebuggingService.Breakpoints>
  <MonoDevelop.Ide.Workbench ActiveDocument="../../../../../../../../../usr/local/share/dotnet/sdk/7.0.402/Sdks/Microsoft.NET.Sdk/targets/Microsoft.NET.TargetFrameworkInference.targets">
    <Files>
      <File FileName="../../../../../../../../../usr/local/share/dotnet/sdk/7.0.402/Sdks/Microsoft.NET.Sdk/targets/Microsoft.NET.TargetFrameworkInference.targets" Line="160" Column="5" />
    </Files>
    <Pads>
      <Pad Id="ProjectPad">
        <State name="__root__">
          <Node name="serverV2" selected="True">
            <Node name="serverV2" expanded="True" />
          </Node>
        </State>
      </Pad>
    </Pads>
  </MonoDevelop.Ide.Workbench>
</Properties>